<?xml version="1.0" encoding="utf-8"?>
<association id="ad7f0383-5ab5-4fbb-98ff-2f42887e7525">
  <sourceEnd id="d30e0569-1dc1-4876-9d4b-38bd89e0c913" type="Association Source End" typeId="8d9d2e5b-bd55-4f36-9ae4-2b9e84fd4e58">
    <name>Invites</name>
    <display>Invites: Invite[*]</display>
    <order>35</order>
    <typeReference id="bf92e945-6020-43d4-bf87-30e1a5655d4f">
      <typeId>a94ef440-060b-4830-8152-8bb2cdbb98bb</typeId>
      <isNavigable>true</isNavigable>
      <isNullable>false</isNullable>
      <isCollection>true</isCollection>
      <isRequired>true</isRequired>
      <typePackageName>AndersonAPI.Domain</typePackageName>
      <typePackageId>bd422e58-8c8c-486a-b9d0-640d2b8f0945</typePackageId>
      <stereotypes />
      <genericTypeParameters />
    </typeReference>
    <stereotypes />
    <metadata />
    <childElements />
  </sourceEnd>
  <targetEnd id="ad7f0383-5ab5-4fbb-98ff-2f42887e7525" type="Association Target End" typeId="0a66489f-30aa-417b-a75d-b945863366fd">
    <name>Company</name>
    <display>Company: Company</display>
    <order>3</order>
    <typeReference id="9b71bb6f-a043-4aca-b1c9-b557034eff3d">
      <typeId>3259289c-5d51-46cb-8c99-78751b456c44</typeId>
      <isNavigable>true</isNavigable>
      <isNullable>false</isNullable>
      <isCollection>false</isCollection>
      <isRequired>true</isRequired>
      <typePackageName>AndersonAPI.Domain</typePackageName>
      <typePackageId>bd422e58-8c8c-486a-b9d0-640d2b8f0945</typePackageId>
      <stereotypes />
      <genericTypeParameters />
    </typeReference>
    <stereotypes />
    <metadata />
    <childElements />
  </targetEnd>
  <associationType>Association</associationType>
  <associationTypeId>eaf9ed4e-0b61-4ac1-ba88-09f912c12087</associationTypeId>
  <stereotypes />
</association>